{"cameraMode":{"drawMode":0,"name":"Shaded","section":"Shading Mode"},"sceneLighting":true,"audioPlay":false,"sceneViewState":{"m_AlwaysRefresh":false,"showFog":true,"showSkybox":true,"showFlares":true,"showImageEffects":true,"showParticleSystems":true,"showVisualEffectGraphs":true,"m_FxEnabled":true},"in2DMode":false,"pivot":{"x":2.11860728263855,"y":1.4799976348876954,"z":0.20000000298023225},"rotation":{"x":-0.06654705107212067,"y":0.012565817683935166,"z":-0.0008395281038247049,"w":-0.9977250099182129},"size":1.353410005569458,"orthographic":false}